daybetter_python/__init__.py
daybetter_python/client.py
daybetter_python/exceptions.py
daybetter_python/py.typed
daybetter_services_python-1.0.7.dist-info/licenses/LICENSE
daybetter_services_python-1.0.7.dist-info/METADATA
daybetter_services_python-1.0.7.dist-info/WHEEL
daybetter_services_python-1.0.7.dist-info/top_level.txt
daybetter_services_python-1.0.7.dist-info/RECORD
