Metadata-Version: 2.4
Name: daybetter-services-python
Version: 1.0.7
Summary: Python client for DayBetter devices and services
Home-page: https://github.com/THDayBetter/daybetter-python
Author: THDayBetter
Author-email: THDayBetter <chenp2368@163.com>
Maintainer-email: THDayBetter <chenp2368@163.com>
License-Expression: MIT
Project-URL: Homepage, https://github.com/THDayBetter/daybetter-python
Project-URL: Documentation, https://github.com/THDayBetter/daybetter-python#readme
Project-URL: Repository, https://github.com/THDayBetter/daybetter-python.git
Project-URL: Bug Tracker, https://github.com/THDayBetter/daybetter-python/issues
Keywords: daybetter,iot,home automation,mqtt
Classifier: Development Status :: 4 - Beta
Classifier: Intended Audience :: Developers
Classifier: Operating System :: OS Independent
Classifier: Programming Language :: Python :: 3
Classifier: Programming Language :: Python :: 3.8
Classifier: Programming Language :: Python :: 3.9
Classifier: Programming Language :: Python :: 3.10
Classifier: Programming Language :: Python :: 3.11
Classifier: Programming Language :: Python :: 3.12
Classifier: Typing :: Typed
Requires-Python: >=3.8
License-File: LICENSE
Requires-Dist: aiohttp>=3.8.0
Provides-Extra: dev
Requires-Dist: pytest>=6.0; extra == "dev"
Requires-Dist: pytest-asyncio; extra == "dev"
Requires-Dist: black; extra == "dev"
Requires-Dist: isort; extra == "dev"
Requires-Dist: flake8; extra == "dev"
Requires-Dist: mypy; extra == "dev"
Dynamic: author
Dynamic: home-page
Dynamic: license-file
Dynamic: requires-python
